compETAG-0.0.3.data/scripts/compute_etags
comp_etag/__init__.py
comp_etag/argsParser.py
comp_etag/core.py
comp_etag/version.py
compETAG-0.0.3.dist-info/LICENSE
compETAG-0.0.3.dist-info/METADATA
compETAG-0.0.3.dist-info/WHEEL
compETAG-0.0.3.dist-info/top_level.txt
compETAG-0.0.3.dist-info/RECORD
