Metadata-Version: 2.1
Name: compETAG
Version: 0.0.3
Summary: The tool provides methods to calculate ETags for Objects on AWS S3, and also md5s, on local objects. It also allows to check the integrity of files, both locally and on AWS S3.
Home-page: https://github.com/awnimo/compETAG
Author: Awni Mousa
Author-email: awnimousa@gmail.com
License: UNKNOWN
Platform: UNKNOWN
Classifier: Programming Language :: Python :: 3
Classifier: License :: OSI Approved :: MIT License
Classifier: Operating System :: OS Independent
Requires-Python: >=3.6
Requires-Dist: numpy
Requires-Dist: boto3
